pylearning/__init__.py
pylearning/ensembles.py
pylearning/node.py
pylearning/trees.py
pylearning/clustering/__init__.py
pylearning/clustering/dbscan.py
pylearning/clustering/kmeans.py
pylearning/ensembles/__init__.py
pylearning/ensembles/ensembles.py
pylearning/neighbours/__init__.py
pylearning/neighbours/neighbours.py
pylearning/trees/__init__.py
pylearning/trees/node.py
pylearning/trees/trees.py
pylearning-3.2.2b1.dist-info/DESCRIPTION.rst
pylearning-3.2.2b1.dist-info/METADATA
pylearning-3.2.2b1.dist-info/RECORD
pylearning-3.2.2b1.dist-info/WHEEL
pylearning-3.2.2b1.dist-info/metadata.json
pylearning-3.2.2b1.dist-info/top_level.txt
