Metadata-Version: 2.0
Name: pylearning
Version: 3.2.2b1
Summary: Simple high-level library to use machine learning algorithms
Home-page: https://github.com/amstuta/pylearning.git
Author: Arthur Amstutz
Author-email: arthur.amstutz@gmail.com
License: MIT
Keywords: machine learning data decision trees random forest nearest neighbours kmeans clustering
Platform: UNKNOWN
Classifier: Development Status :: 4 - Beta
Classifier: Intended Audience :: Developers
Classifier: Topic :: Scientific/Engineering :: Artificial Intelligence
Classifier: License :: OSI Approved :: MIT License
Classifier: Programming Language :: Python :: 3
Classifier: Programming Language :: Python :: 3.3
Classifier: Programming Language :: Python :: 3.4
Classifier: Programming Language :: Python :: 3.5
Requires-Dist: numpy
